LICENSE.txt
README.md
long-description.rst
rainbow/__init__.py
rainbow/helpers.py
rainbow/rainbow.py
res/rainbow-logger-output.png
test.py
rainbow_bridge_logger-0.7.0.dist-info/LICENSE.txt
rainbow_bridge_logger-0.7.0.dist-info/WHEEL
rainbow_bridge_logger-0.7.0.dist-info/METADATA
rainbow_bridge_logger-0.7.0.dist-info/RECORD
